<!-- ルナトくん -->
<Avatar>
    <NAME>Lunato</NAME>
    <Hips>Hips</Hips>
    <LeftUpperLeg>UpperLeg_L</LeftUpperLeg>
    <RightUpperLeg>UpperLeg_R</RightUpperLeg>
    <LeftLowerLeg>LowerLeg_L</LeftLowerLeg>
    <RightLowerLeg>LowerLeg_R</RightLowerLeg>
    <LeftFoot>Foot_L</LeftFoot>
    <RightFoot>Foot_R</RightFoot>
    <Spine>Spine</Spine>
    <Chest>Chest</Chest>
    <Neck>Neck</Neck>
    <Head>Head</Head>
    <LeftShoulder>Shoulder_L</LeftShoulder>
    <RightShoulder>Shoulder_R</RightShoulder>
    <LeftUpperArm>UpperArm_L</LeftUpperArm>
    <RightUpperArm>UpperArm_R</RightUpperArm>
    <LeftLowerArm>LowerArm_L</LeftLowerArm>
    <RightLowerArm>LowerArm_R</RightLowerArm>
    <LeftHand>Hand_L</LeftHand>
    <RightHand>Hand_R</RightHand>
    <LeftToes>Toe_L</LeftToes>
    <RightToes>Toe_R</RightToes>
    <LeftEye>LeftEye</LeftEye>
    <RightEye>RightEye</RightEye>
    <Jaw>NONE</Jaw>
    <LeftThumbProximal>Thumb_1_L</LeftThumbProximal>
    <LeftThumbIntermediate>Thumb_2_L</LeftThumbIntermediate>
    <LeftThumbDistal>Thumb_3_L</LeftThumbDistal>
    <LeftIndexProximal>Index_1_L</LeftIndexProximal>
    <LeftIndexIntermediate>Index_2_L</LeftIndexIntermediate>
    <LeftIndexDistal>Index_3_L</LeftIndexDistal>
    <LeftMiddleProximal>Middle_1_L</LeftMiddleProximal>
    <LeftMiddleIntermediate>Middle_2_L</LeftMiddleIntermediate>
    <LeftMiddleDistal>Middle_3_L</LeftMiddleDistal>
    <LeftRingProximal>Ring_1_L</LeftRingProximal>
    <LeftRingIntermediate>Ring_2_L</LeftRingIntermediate>
    <LeftRingDistal>Ring_3_L</LeftRingDistal>
    <LeftLittleProximal>Little_1_L</LeftLittleProximal>
    <LeftLittleIntermediate>Little_2_L</LeftLittleIntermediate>
    <LeftLittleDistal>Little_3_L</LeftLittleDistal>
    <RightThumbProximal>Thumb_1_R</RightThumbProximal>
    <RightThumbIntermediate>Thumb_2_R</RightThumbIntermediate>
    <RightThumbDistal>Thumb_3_R</RightThumbDistal>
    <RightIndexProximal>Index_1_R</RightIndexProximal>
    <RightIndexIntermediate>Index_2_R</RightIndexIntermediate>
    <RightIndexDistal>Index_3_R</RightIndexDistal>
    <RightMiddleProximal>Middle_1_R</RightMiddleProximal>
    <RightMiddleIntermediate>Middle_2_R</RightMiddleIntermediate>
    <RightMiddleDistal>Middle_3_R</RightMiddleDistal>
    <RightRingProximal>Ring_1_R</RightRingProximal>
    <RightRingIntermediate>Ring_2_R</RightRingIntermediate>
    <RightRingDistal>Ring_3_R</RightRingDistal>
    <RightLittleProximal>Little_1_R</RightLittleProximal>
    <RightLittleIntermediate>Little_2_R</RightLittleIntermediate>
    <RightLittleDistal>Little_3_R</RightLittleDistal>
    <UpperChest>NONE</UpperChest>
    <LastBone>NONE</LastBone>
    ------Options------
    <RightBreastRoot>NONE</RightBreastRoot>
    <RightBreastMid>NONE</RightBreastMid>
    <RightBreastEnd>NONE</RightBreastEnd>
    <LeftBreastRoot>NONE</LeftBreastRoot>
    <LeftBreastMid>NONE</LeftBreastMid>
    <LeftBreastEnd>NONE</LeftBreastEnd>
</Avatar>